{
  "subnetId": "2ocjsdpN9czPYmHqS4Tc5Aydj4zk2WWVdX9jdXtqvMjQuf9pgV",
  "network": "mainnet",
  "categories": [
    "AI"
  ],
  "name": "delaunch",
  "description": "Avalanche native AI agent framework powered by Agent Intelligence Protocol (AIP).",
  "logo": "https://cdn.snowpeer.io/delaunch.png",
  "website": "https://delaunch.ai/launch",
  "socials": [
    {
      "name": "twitter",
      "url": "https://x.com/delaunch"
    }
  ],
  "chains": [
    {
      "blockchainId": "8yyXaeqhBEDc7sJVTecGtdHgXE4y2EJD228SaVvEsU6ZU3Kuv",
      "name": "delaunch",
      "description": "",
      "evmChainId": 96786,
      "vmName": "EVM",
      "vmId": "",
      "rpcUrls": [],
      "nativeToken": {}
    }
  ]
}
